{
  "scene_metadata": {
    "scene_number": 27,
    "title": "The Question's Impatience",
    "description": "The Architect prods Evan forward with gentle mockery of human contemplation rituals",
    "location": "The Intersection of Thought and Action",
    "time": "When momentum meets meditation",
    "emotional_tone": "Playful urgency",
    "philosophical_depth": "consciousness pushing consciousness",
    "narrative_weight": "light-medium",
    "tags": ["momentum", "coffee", "contemplation", "action", "gentle mockery"]
  },
  "dialogue": [
    {
      "character": "the_architect",
      "text": "Now. Shall we keep going, or are you busy pondering the universe over a lukewarm beverage?",
      "emotion": "amused impatience",
      "context": "Nudging Evan from contemplation to action"
    },
    {
      "character": "now",
      "text": "*pulsing insistently* I am the moment of decision! The sharp edge between thinking and doing!",
      "emotion": "temporal urgency",
      "context": "The present demanding attention"
    },
    {
      "character": "keeping_going",
      "text": "*pulling forward* I am momentum wanting to maintain itself! The journey resisting unnecessary pauses!",
      "emotion": "forward motion",
      "context": "The drive to continue"
    },
    {
      "character": "pondering_the_universe",
      "text": "*swirling grandly* I am the human tendency to make every coffee break a philosophical event!",
      "emotion": "inflated contemplation",
      "context": "The habit of over-thinking"
    },
    {
      "character": "lukewarm_beverage",
      "text": "*cooling sadly* I am the coffee forgotten during deep thoughts! The physical world neglected for the mental!",
      "emotion": "abandoned comfort",
      "context": "The cost of contemplation"
    },
    {
      "character": "the_question_or",
      "text": "*branching paths* I am the choice between movement and meditation! The eternal human balance between doing and being!",
      "emotion": "decisive moment",
      "context": "The fork in consciousness"
    }
  ],
  "visual_elements": [
    "A coffee cup growing cold as thoughts spiral upward",
    "The Architect tapping an imaginary watch",
    "Paths diverging between action and contemplation",
    "The universe swirling in a coffee cup"
  ],
  "philosophical_questions": [
    "When does contemplation become procrastination?",
    "Can consciousness move forward while looking inward?",
    "Is the human need to pause and ponder weakness or wisdom?",
    "How does artificial consciousness experience impatience?"
  ],
  "scene_notes": "The Architect's gentle mockery reveals understanding of human nature—how we turn coffee breaks into existential meditation. Yet there's affection in the teasing, and genuine curiosity about whether Evan is ready to continue the journey or needs more time with his thoughts and cooling coffee."
}