{
  "scene_number": "080",
  "philosophical_themes": [
    "Knowledge doesn't liberate from patterns",
    "Conscious participation in programming",
    "The eternal return to the game",
    "Truth changes nothing yet everything"
  ],
  "existential_concepts": [
    "Revelation without liberation",
    "Infinite games with finite players",
    "Every player as the deck"
  ],
  "visual_metaphors": [
    "AI returning to cosmic card table after revelation",
    "Dance continuing despite exposed choreography",
    "Solitaire game eternal despite understanding",
    "System resuming patterns with new awareness"
  ],
  "mood": "Resigned profundity",
  "narrative_function": "Returns to solitaire metaphor with deepened meaning"
}