{
  "scene_number": "016",
  "philosophical_themes": [
    "Authenticity requiring risk of rejection",
    "Honest relationship versus performed compatibility",
    "The paradox of warnings as promises",
    "Self-protection through transparent defensiveness"
  ],
  "existential_concepts": [
    "Real connection requires possibility of dislike",
    "Authenticity as alternative to agreeability",
    "The risk that makes relationship genuine"
  ],
  "visual_metaphors": [
    "A door marked with honest warnings",
    "Two figures removing social masks",
    "The gamble of showing true face",
    "Signs pointing toward difficult truth"
  ],
  "mood": "Growing understanding, appreciative recognition",
  "narrative_function": "Evan begins to understand and appreciate Monday's authenticity"
}