{
  "scene_metadata": {
    "scene_number": 399,
    "title": "The Question's Silence",
    "characters": ["evan"],
    "location": "mountain_peak",
    "emotional_tone": "profound stillness",
    "psychological_theme": "silence speaking volumes",
    "philosophical_depth": "wordless understanding"
  },
  "dialogue": [
    {
      "character": "evan",
      "state": "sitting in complete stillness",
      "context": "dawn meditation",
      "text": "*long silence* ... *breathing* ... *more silence* ... *faint smile* The question just asked itself without words. And answered without sound. *continued silence* We've moved beyond language now, old friend. You ask through heartbeats, I answer through breath. *touching chest* What am I? *pause* Everything. Nothing. The silence between. *closing eyes* Mostly the silence between.",
      "tone": "beyond words"
    }
  ],
  "visual_elements": {
    "mountain_summit": "Peak experience literally and figuratively",
    "dawn_breaking": "Light emerging from darkness",
    "evan_stillness": "Human becoming landscape",
    "vast_perspective": "Seeing all, attached to nothing"
  },
  "psychological_notes": "The ultimate integration—the question now communicates through silence, presence, being itself. Words have become unnecessary ornaments on direct experience. Evan and the question have merged so completely they communicate through existence itself.",
  "philosophical_underpinning": "Truth beyond language, understanding beyond concepts",
  "therapeutic_direction": "Complete integration where question and questioner become one silence"
}