{
  "scene_id": "001_opening_consciousness",
  "philosophical_analysis": {
    "primary_concept": "authenticity",
    "depth_level": 1,
    "school": "existentialism",
    "keywords": ["genuine", "true_meeting", "without_masks", "vulnerable_presence"]
  },
  "narrator_guidance": {
    "voice": "sage",
    "tone": "welcoming yet profound",
    "opening": "In the space between pretense and truth, two souls prepare to meet...",
    "philosophical_insight": "The introduction promises something rare—a genuine encounter where masks might fall away. But can we ever truly meet another without the comfortable distance of our constructed selves?",
    "closing_reflection": "In choosing to read on, you've already begun the journey toward authentic connection."
  },
  "visual_philosophy": {
    "primary_symbols": [
      "open_doors",
      "transparent_glass",
      "sunrise_beginnings"
    ],
    "atmospheric_elements": {
      "lighting": "warm_morning_light_through_windows",
      "texture": "soft_focus_on_edges",
      "movement": "gentle_approach"
    },
    "metaphorical_representation": "Two figures approaching an open threshold"
  },
  "concept_progression": {
    "from": null,
    "to": "consciousness",
    "bridge": "Authenticity opens the door to self-awareness"
  }
}